LICENSE
MANIFEST.in
README.md
pyproject.toml
setup.cfg
setup.py
Shiprocket_sdk.egg-info/PKG-INFO
Shiprocket_sdk.egg-info/SOURCES.txt
Shiprocket_sdk.egg-info/dependency_links.txt
Shiprocket_sdk.egg-info/requires.txt
Shiprocket_sdk.egg-info/top_level.txt
shiprocket/__init__.py
shiprocket/auth/__init__.py
shiprocket/auth/access_token_response.py
shiprocket/auth/credentials.py
shiprocket/auth/exceptions.py
shiprocket/auth/shiprocket_client.py
shiprocket/resources/__init__.py
shiprocket/resources/base.py
shiprocket/resources/channel.py
shiprocket/resources/courier.py
shiprocket/resources/labels_manifest_invoice.py
shiprocket/resources/order.py
shiprocket/resources/pickup_address.py
shiprocket/resources/product.py
shiprocket/resources/return_order.py
shiprocket/resources/shipment.py