Metadata-Version: 2.1
Name: Shiprocket-sdk
Version: 1.0.2
Summary: This is the python client for the shiprocket
Home-page: https://github.com/singhAnike/shiprocket.git
Author: Aniket Singh
Author-email: singh7509811123@gmail.com
License: UNKNOWN
Keywords: python client for the uses of the shiprocket
Platform: UNKNOWN
License-File: LICENSE
